lamina/__init__.py
lamina/conf.py
lamina/helpers.py
lamina/hooks.py
lamina/main.py
lamina/openapi/__init__.py
lamina/openapi/generator.py
lamina/openapi/markdown.py
lamina/openapi/types.py
lamina/openapi/view_data.py
lamina/spec.py
py_lamina-6.2.9.dist-info/METADATA
py_lamina-6.2.9.dist-info/WHEEL
py_lamina-6.2.9.dist-info/licenses/LICENSE
py_lamina-6.2.9.dist-info/RECORD
