Metadata-Version: 2.4
Name: py-lamina
Version: 6.2.9
Summary: Add a new layer ("lâmina") to AWS lambda functions
License: MIT
License-File: LICENSE
Keywords: aws,lambda,decorator
Author: Chris Maillefaud
Author-email: chrismaille@users.noreply.github.com
Requires-Python: >=3.11,<4
Classifier: Development Status :: 4 - Beta
Classifier: Environment :: Plugins
Classifier: Intended Audience :: Developers
Classifier: License :: OSI Approved :: MIT License
Classifier: Programming Language :: Python :: 3
Classifier: Programming Language :: Python :: 3.11
Classifier: Programming Language :: Python :: 3.12
Classifier: Programming Language :: Python :: 3.13
Classifier: Programming Language :: Python :: 3.14
Requires-Dist: asgiref
Requires-Dist: case-converter
Requires-Dist: loguru
Requires-Dist: mistune
Requires-Dist: pydantic
Requires-Dist: python-magic
Project-URL: Repository, https://github.com/megalus/lamina
